{
  "schemaVersion": 1,
  "id": "chiselmon",
  "version": "${version}",
  "name": "Chiselmon",
  "description": "Smooth out your Cobblemon experience!",
  "authors": [
    "megaturtl"
  ],
  "contact": {
    "homepage": "https://turtl.cc"
  },
  "license": "MIT",
  "icon": "assets/chiselmon/icon.png",
  "environment": "*",
  "entrypoints": {
    "main": [
      "cc.turtl.chiselmon.fabric.ChiselmonFabric"
    ],
    "client": [
      "cc.turtl.chiselmon.fabric.client.ChiselmonFabricClient"
    ]
  },
  "mixins": [
    "chiselmon.mixins.json"
  ],
  "depends": {
    "fabricloader": ">=0.18.4",
    "minecraft": "~1.21.1",
    "java": ">=21",
    "architectury": ">=13.0.8",
    "fabric-api": "*"
  },
  "suggests": {
    "another-mod": "*"
  }
}
